licence/__init__.py
licence/licence.py
licence/licenses/AGPL-3.0+.txt
licence/licenses/AGPL-3.0.txt
licence/licenses/Apache-1.0.txt
licence/licenses/Apache-1.1.txt
licence/licenses/Apache-2.0.txt
licence/licenses/BSD-2-Clause.txt
licence/licenses/BSD-3-Clause.txt
licence/licenses/EUPL-1.2.txt
licence/licenses/GPL-2.0+.txt
licence/licenses/GPL-2.0.txt
licence/licenses/GPL-3.0+.txt
licence/licenses/GPL-3.0.txt
licence/licenses/LGPL-2.1+.txt
licence/licenses/LGPL-2.1.txt
licence/licenses/LGPL-3.0+.txt
licence/licenses/LGPL-3.0.txt
licence/licenses/MIT.txt
licence/licenses/NoLicense.txt
licence-0.1.1.dist-info/LICENSE
licence-0.1.1.dist-info/WHEEL
licence-0.1.1.dist-info/METADATA
licence-0.1.1.dist-info/RECORD
