Metadata-Version: 2.1
Name: licence
Version: 0.1.1
Summary: License texts and header strings.
Keywords: license,osi
Author-email: Stephan Helma <s.p.helma@gmx.net>
Requires-Python: >=3.6
Classifier: Programming Language :: Python :: 3
Classifier: License :: OSI Approved :: GNU Lesser General Public License v3 or later (LGPLv3+)
Classifier: Operating System :: OS Independent
Classifier: Development Status :: 4 - Beta
Project-URL: Homepage, https://codeberg.org/sph/licence
Project-URL: Issues, https://codeberg.org/sph/licence/issues
